Workbook

Sheet Resumen TEC
A1: SIGET — Planilla de Tiempo, Esfuerzo y Costo (TEC)
A3: Proyecto | B3: SIGET — Sistema Integral de Gestión de Equipos y Soporte Tecnológico | D3: Resumen presupuestario | E3: CLP
A4: Duración | B4: ='Supuestos'!B4 -> 7 sprints / 13/08/2026 al 05/11/2026 | D4: Costos planificados identificados | E4: ='Costos y Presupuesto'!C9 -> 14700000
A5: Equipo | B5: Joaquín Riquelme · Diego Alcaíno · Ignacio Troncoso | D5: Saldo no asignado presupuesto base | E5: =E6-E4 -> 1300000
A6: HH planificadas | B6: ='HH por Integrante'!C7 -> 900 | D6: Presupuesto base | E6: 16000000
A7: Tarifa referencial | B7: 15000 | D7: Contingencia adicional | E7: 0.1
A8: Costo HH | B8: =B6*B7 -> 13500000 | D8: Reserva de contingencia | E8: =E6*E7 -> 1600000
D9: Máximo con contingencia | E9: =E6+E8 -> 17600000
A11: Criterio TEC aplicado
A12: La estimación de referencia es de 900 HH, distribuidas entre tres integrantes y siete sprints. El costo del trabajo se valoriza con una tarifa referencial. El seguimiento acumula las horas registradas y proyecta el costo pendiente. El presupuesto base y la reserva de contingencia se mantienen separados.
A16: Seguimiento de ejecución
A18: HH registradas | B18: ='Seguimiento por Sprint'!D11 -> 534.5 | D18: Costo HH registrado | E18: ='Costos y Presupuesto'!C19 -> 8017500
A19: HH pendientes (plan) | B19: =SUMIF('Seguimiento por Sprint'!D4:D10,"",'Seguimiento por Sprint'!C4:C10) -> 300 | D19: Desarrollo pendiente (plan) | E19: ='Costos y Presupuesto'!C20 -> 4500000
A20: Sprints con horas registradas | B20: =COUNT('Seguimiento por Sprint'!D4:D10) -> 6 | D20: Otros costos estimados | E20: ='Costos y Presupuesto'!C21 -> 1200000
D21: Costo total proyectado | E21: ='Costos y Presupuesto'!C22 -> 13717500
D22: Holgura del presupuesto | E22: ='Costos y Presupuesto'!C23 -> 2282500
A24: El costo registrado valoriza el esfuerzo. La proyección incorpora el trabajo pendiente y los costos no laborales estimados.

Sheet HH por Integrante
A1: Estimación de Horas-Hombre por integrante
A3: Integrante | B3: Rol principal en SIGET | C3: HH estimadas | D3: Tarifa CLP/HH | E3: Costo estimado
A4: Joaquín Riquelme | B4: Product Owner / Gerente de Proyecto / Desarrollador | C4: 300 | D4: ='Resumen TEC'!$B$7 -> 15000 | E4: =C4*D4 -> 4500000
A5: Diego Alcaíno | B5: Scrum Master / Frontend / UX / Documentación | C5: 300 | D5: ='Resumen TEC'!$B$7 -> 15000 | E5: =C5*D5 -> 4500000
A6: Ignacio Troncoso | B6: Developer / Web / PySide6 / Docker | C6: 300 | D6: ='Resumen TEC'!$B$7 -> 15000 | E6: =C6*D6 -> 4500000
A7: TOTAL | C7: =SUM(C4:C6) -> 900 | E7: =SUM(E4:E6) -> 13500000

Sheet Esfuerzo por Fase
A1: Distribución inicial del esfuerzo TEC — SIGET
A3: Fase / actividad | B3: Joaquín HH | C3: Diego HH | D3: Ignacio HH | E3: Total HH | F3: % esfuerzo
A4: Requerimientos y planificación | B4: 35 | C4: 35 | D4: 20 | E4: =SUM(B4:D4) -> 90 | F4: =E4/$E$12 -> 0.1
A5: Arquitectura y diseño | B5: 45 | C5: 40 | D5: 35 | E5: =SUM(B5:D5) -> 120 | F5: =E5/$E$12 -> 0.13333333
A6: Base de datos | B6: 40 | C6: 20 | D6: 60 | E6: =SUM(B6:D6) -> 120 | F6: =E6/$E$12 -> 0.13333333
A7: Backend y APIs | B7: 65 | C7: 45 | D7: 70 | E7: =SUM(B7:D7) -> 180 | F7: =E7/$E$12 -> 0.2
A8: Plataforma Web | B8: 30 | C8: 60 | D8: 30 | E8: =SUM(B8:D8) -> 120 | F8: =E8/$E$12 -> 0.13333333
A9: Aplicación Escritorio PySide6 | B9: 25 | C9: 30 | D9: 50 | E9: =SUM(B9:D9) -> 105 | F9: =E9/$E$12 -> 0.11666667
A10: QA, seguridad e integración | B10: 35 | C10: 45 | D10: 25 | E10: =SUM(B10:D10) -> 105 | F10: =E10/$E$12 -> 0.11666667
A11: Documentación y despliegue | B11: 25 | C11: 25 | D11: 10 | E11: =SUM(B11:D11) -> 60 | F11: =E11/$E$12 -> 0.066666667
A12: TOTAL | B12: =SUM(B4:B11) -> 300 | C12: =SUM(C4:C11) -> 300 | D12: =SUM(D4:D11) -> 300 | E12: =SUM(E4:E11) -> 900 | F12: =SUM(F4:F11) -> 1

Sheet Costos y Presupuesto
A1: Estimación de Costos — SIGET
A3: Concepto | B3: Base de cálculo | C3: Estimación CLP | D3: Observación
A4: Desarrollo — 3 integrantes | B4: HH planificadas × tarifa referencial | C4: ='HH por Integrante'!E7 -> 13500000 | D4: Valorización referencial del esfuerzo
A5: Hosting/servidor e infraestructura | B5: Estimación del proyecto | C5: 600000 | D5: Infraestructura de desarrollo/despliegue
A6: Dominio, correo y servicios externos/APIs | B6: Estimación del proyecto | C6: 250000 | D6: Servicios tecnológicos externos
A7: Equipamiento/periféricos y pruebas | B7: Estimación del proyecto | C7: 350000 | D7: QR, periféricos y validación
A8: Herramientas/licencias base | B8: Tecnologías open source | C8: 0 | D8: Costo de licenciamiento estimado en $0 por el Stack base de código abierto.
A9: Costos planificados identificados | C9: =SUM(C4:C8) -> 14700000 | D9: Suma de costos actualmente fundamentados
A10: Saldo no asignado presupuesto base | B10: $16.000.000 - costos identificados | C10: =C11-C9 -> 1300000 | D10: Holgura del presupuesto base; no es contingencia
A11: PRESUPUESTO BASE | C11: 16000000 | D11: Monto base definido para SIGET
A12: Contingencia adicional | B12: 10% del presupuesto base | C12: =C11*'Resumen TEC'!$E$7 -> 1600000 | D12: Uso exclusivo ante emergencias/variaciones justificadas
A13: PRESUPUESTO MÁXIMO | B13: Base + contingencia | C13: =C11+C12 -> 17600000 | D13: Máximo si se utiliza el 100% de la reserva
A15: Nota: el saldo no asignado dentro del presupuesto base no debe confundirse con la reserva de contingencia adicional del 10%.
A17: Seguimiento y proyección de costos
A19: Desarrollo registrado | B19: HH registradas × tarifa | C19: ='Seguimiento por Sprint'!G11 -> 8017500 | D19: Valorización acumulada de los sprints con horas registradas.
A20: Desarrollo pendiente (plan) | B20: HH sin registro × tarifa | C20: ='Resumen TEC'!B19*'Resumen TEC'!$B$7 -> 4500000 | D20: Esfuerzo planificado de los sprints pendientes de cierre.
A21: Otros costos estimados | B21: Infraestructura, servicios y equipos | C21: =SUM(C5:C8) -> 1200000 | D21: Estimaciones no laborales del presupuesto.
A22: COSTO TOTAL PROYECTADO | C22: =SUM(C19:C21) -> 13717500 | D22: Desarrollo registrado, trabajo pendiente y otros costos estimados.
A23: Holgura del presupuesto base | C23: =C11-C22 -> 2282500 | D23: Presupuesto base menos costo total proyectado.

Sheet Seguimiento por Sprint
A1: Seguimiento de tiempo, esfuerzo y costo por sprint
A3: Sprint | B3: Periodo / foco | C3: HH planificadas | D3: HH registradas | E3: Desviación HH | F3: Costo planificado | G3: Costo HH registrado | H3: Estado
A4: Sprint 1 | B4: 13/08–26/08: Definición y fundamentación del proyecto. | C4: 100 | D4: 32 | E4: =IF(ISNUMBER(D4),D4-C4,"") -> -68 | F4: =C4*'Resumen TEC'!$B$7 -> 1500000 | G4: =IF(ISNUMBER(D4),D4*'Resumen TEC'!$B$7,"") -> 480000 | H4: Completado
A5: Sprint 2 | B5: 27/08–09/09: Requerimientos, backlog, arquitectura y diseño. | C5: 100 | D5: 90 | E5: =IF(ISNUMBER(D5),D5-C5,"") -> -10 | F5: =C5*'Resumen TEC'!$B$7 -> 1500000 | G5: =IF(ISNUMBER(D5),D5*'Resumen TEC'!$B$7,"") -> 1350000 | H5: Completado
A6: Sprint 3 | B6: 10/09–14/09: Repositorio, Docker, PostgreSQL y arquitectura inicial. | C6: 100 | D6: 56 | E6: =IF(ISNUMBER(D6),D6-C6,"") -> -44 | F6: =C6*'Resumen TEC'!$B$7 -> 1500000 | G6: =IF(ISNUMBER(D6),D6*'Resumen TEC'!$B$7,"") -> 840000 | H6: Completado
A7: Sprint 4 | B7: 15/09–28/09: Autenticación, acceso e integración del entorno. | C7: 100 | D7: 51 | E7: =IF(ISNUMBER(D7),D7-C7,"") -> -49 | F7: =C7*'Resumen TEC'!$B$7 -> 1500000 | G7: =IF(ISNUMBER(D7),D7*'Resumen TEC'!$B$7,"") -> 765000 | H7: Completado con alcance parcial
A8: Sprint 5 | B8: 29/09–18/10: Activos, asignaciones, entregas, devoluciones y tickets iniciales. | C8: 100 | D8: 230 | E8: =IF(ISNUMBER(D8),D8-C8,"") -> 130 | F8: =C8*'Resumen TEC'!$B$7 -> 1500000 | G8: =IF(ISNUMBER(D8),D8*'Resumen TEC'!$B$7,"") -> 3450000 | H8: Completado
A9: Sprint 6 | B9: 19/10–26/10: Escritorio, tickets y OT, auditoría, correo, avisos, CSAT y catálogos. | C9: 100 | D9: 75.5 | E9: =IF(ISNUMBER(D9),D9-C9,"") -> -24.5 | F9: =C9*'Resumen TEC'!$B$7 -> 1500000 | G9: =IF(ISNUMBER(D9),D9*'Resumen TEC'!$B$7,"") -> 1132500 | H9: Completado
A10: Sprint 7 | B10: 27/10–05/11: Reparación, repuestos, QR, reportes, seguridad, QA y cierre. | C10: 300 | E10: =IF(ISNUMBER(D10),D10-C10,"") | F10: =C10*'Resumen TEC'!$B$7 -> 4500000 | G10: =IF(ISNUMBER(D10),D10*'Resumen TEC'!$B$7,"") | H10: En curso
A11: TOTAL | C11: =SUM(C4:C10) -> 900 | D11: =IF(COUNT(D4:D10)=0,"",SUM(D4:D10)) -> 534.5 | E11: =IF(COUNT(D4:D10)=0,"",SUM(E4:E10)) -> -65.5 | F11: =SUM(F4:F10) -> 13500000 | G11: =IF(COUNT(G4:G10)=0,"",SUM(G4:G10)) -> 8017500
A14: Las HH registradas corresponden a los registros de actividades de cada sprint y son estimaciones de dedicación. Se incorporan al seguimiento al cerrar el sprint.
A15: La desviación acumulada compara únicamente los sprints con horas registradas. El Sprint 7 concentra las actividades pendientes de desarrollo, integración, pruebas y cierre.

Sheet Supuestos
A1: Supuestos y criterios de estimación
A3: Ítem | B3: Valor / criterio | C3: Tipo | D3: Observación
A4: Periodo del proyecto | B4: =B18&" sprints / "&TEXT(B15,"dd/mm/yyyy")&" al "&TEXT(B16,"dd/mm/yyyy") -> 7 sprints / 13/08/2026 al 05/11/2026 | C4: Definido | D4: Planificación vigente de siete sprints.
A5: Equipo | B5: 3 integrantes | C5: Definido | D5: Joaquín, Diego e Ignacio
A6: HH totales | B6: 900 HH | C6: Definido | D6: 300 HH por integrante
A7: Dedicación media planificada | B7: ='HH por Integrante'!C4/B17 -> 25 | C7: Derivado | D7: HH por integrante / semanas del periodo.
A8: Tarifa referencial | B8: $15.000 CLP/HH | C8: Supuesto de valorización | D8: No representa remuneración real
A9: Presupuesto base | B9: $16.000.000 CLP | C9: Definido | D9: Separado de la contingencia
A10: Contingencia | B10: 10% adicional = $1.600.000 CLP | C10: Definido | D10: Solo emergencias o variaciones justificadas
A12: Referencia metodológica: una planilla TEC separa tiempo, esfuerzo y costo; las plantillas de proyectos TI suelen relacionar fases, HH, tasas laborales, costos adicionales y total del proyecto.
A13: Fuentes de referencia: https://es.scribd.com/document/725105335/PlanillaTEC | https://es.smartsheet.com/content/project-cost-templates
A15: Inicio del periodo | B15: 46247 | C15: Fecha
A16: Cierre del periodo | B16: 46331 | C16: Fecha
A17: Duración en semanas | B17: =(B16-B15)/7 -> 12 | C17: Derivado
A18: Número de sprints | B18: 7 | C18: Planificado | D18: Las actividades pendientes se concentran en el Sprint 7.
A20: Criterio de seguimiento | B20: HH estimadas de dedicación según los registros de actividades de cada sprint. | C20: Registro | D20: El costo de HH es una valorización referencial del esfuerzo.
